MANIFEST.in
README.rst
setup.py
ajaxutils/__init__.py
ajaxutils/decorators.py
ajaxutils/http.py
ajaxutils/views.py
django_ajaxutils.egg-info/PKG-INFO
django_ajaxutils.egg-info/SOURCES.txt
django_ajaxutils.egg-info/dependency_links.txt
django_ajaxutils.egg-info/requires.txt
django_ajaxutils.egg-info/top_level.txt
django_ajaxutils.egg-info/zip-safe