Metadata-Version: 1.0
Name: django-ajaxutils
Version: 0.2
Summary: Ajax requests for Ponies
Home-page: http://github.com/ahref/django-ajaxutils
Author: UNKNOWN
Author-email: UNKNOWN
License: BSD
Platform: UNKNOWN
Classifier: Development Status :: 4 - Beta
Classifier: Environment :: Web Environment
Classifier: Framework :: Django
Classifier: Intended Audience :: Developers
Classifier: License :: OSI Approved :: BSD License
Classifier: Operating System :: OS Independent
Classifier: Programming Language :: Python
Classifier: Topic :: Utilities
